cruxrec/__init__.py
cruxrec/cli.py
cruxrec/subs_provider.py
cruxrec/summarizer.py
cruxrec/utils.py
cruxrec-0.1.2.dist-info/METADATA
cruxrec-0.1.2.dist-info/WHEEL
cruxrec-0.1.2.dist-info/entry_points.txt
cruxrec-0.1.2.dist-info/top_level.txt
cruxrec-0.1.2.dist-info/RECORD
