Metadata-Version: 2.4
Name: cruxrec
Version: 0.1.2
Summary: A command-line tool to summarize YouTube videos using AI.
Home-page: https://github.com/AShandrakov/CruxRec
Author: Artyom Shandrkov
Author-email: artyom.shandrakov@gmail.com
License: MIT
Classifier: Programming Language :: Python :: 3
Requires-Python: >=3.7
Requires-Dist: certifi
Requires-Dist: charset-normalizer
Requires-Dist: idna
Requires-Dist: PyYAML
Requires-Dist: requests
Requires-Dist: urllib3
Requires-Dist: yt-dlp
Dynamic: author
Dynamic: author-email
Dynamic: classifier
Dynamic: description
Dynamic: description-content-type
Dynamic: home-page
Dynamic: license
Dynamic: requires-dist
Dynamic: requires-python
Dynamic: summary
